conditional_independence/__init__.py
conditional_independence/ci_tests/__init__.py
conditional_independence/ci_tests/ci_tester.py
conditional_independence/ci_tests/nonparametric/__init__.py
conditional_independence/ci_tests/nonparametric/fadcor.py
conditional_independence/ci_tests/nonparametric/hsic.py
conditional_independence/ci_tests/nonparametric/kci.py
conditional_independence/ci_tests/oracle/__init__.py
conditional_independence/ci_tests/oracle/oracle.py
conditional_independence/ci_tests/parametric/__init__.py
conditional_independence/ci_tests/parametric/partial_correlation_test.py
conditional_independence/invariance_tests/__init__.py
conditional_independence/invariance_tests/invariance_tester.py
conditional_independence/invariance_tests/nonparametric/__init__.py
conditional_independence/invariance_tests/nonparametric/hsic.py
conditional_independence/invariance_tests/nonparametric/kci.py
conditional_independence/invariance_tests/oracle/__init__.py
conditional_independence/invariance_tests/oracle/oracle.py
conditional_independence/invariance_tests/parametric/__init__.py
conditional_independence/invariance_tests/parametric/gauss_invariance.py
conditional_independence/suffstats/__init__.py
conditional_independence/suffstats/ci_suffstats/__init__.py
conditional_independence/suffstats/ci_suffstats/partial_correlation_suffstat.py
conditional_independence/suffstats/invariance_suffstats/__init__.py
conditional_independence/suffstats/invariance_suffstats/gauss_invariance_suffstat.py
conditional_independence/utils/__init__.py
conditional_independence/utils/kernels.py
conditional_independence-0.1a6.dist-info/LICENSE.txt
conditional_independence-0.1a6.dist-info/METADATA
conditional_independence-0.1a6.dist-info/WHEEL
conditional_independence-0.1a6.dist-info/top_level.txt
conditional_independence-0.1a6.dist-info/RECORD
